{
    "configurations": [
        {
            "name": "mac - arm64",
            "includePath": [
                "${workspaceFolder}/**",
                "${env:vs_prefix_prj}/include/**",
                "${env:vs_prefix_usr}/include/**",
                "${env:CONDA_PREFIX}/include/**",
                "/Applications/Xcode.app/Contents/Developer/Platforms/MacOSX.platform/Developer/SDKs/MacOSX.sdk/System/Library/Frameworks/**"
            ],
            "defines": [
                "DEBUG",
                "WITH_PYRE",
                "WITH_JOURNAL"
            ],
            "macFrameworkPath": [
                "/Applications/Xcode.app/Contents/Developer/Platforms/MacOSX.platform/Developer/SDKs/MacOSX.sdk/System/Library/Frameworks"
            ],
            "cStandard": "c17",
            "cppStandard": "c++20",
            "intelliSenseMode": "macos-clang-arm64"
        }
    ],
    "version": 4
}
